dbfs_spark_cache/__init__.py
dbfs_spark_cache/cache_management.py
dbfs_spark_cache/caching.py
dbfs_spark_cache/config.py
dbfs_spark_cache/core_caching.py
dbfs_spark_cache/dataframe_extensions.py
dbfs_spark_cache/hashing.py
dbfs_spark_cache/query_complexity_estimation.py
dbfs_spark_cache/utils.py
dbfs_spark_cache-0.5.1.dist-info/METADATA
dbfs_spark_cache-0.5.1.dist-info/WHEEL
dbfs_spark_cache-0.5.1.dist-info/licenses/LICENSE
dbfs_spark_cache-0.5.1.dist-info/licenses/NOTICE
dbfs_spark_cache-0.5.1.dist-info/RECORD
