Metadata-Version: 2.4
Name: dbfs-spark-cache
Version: 0.5.1
Summary: A utility for caching Spark DataFrames in Databricks File System
Project-URL: Homepage, https://github.com/schibsted/dbfs-spark-cache
Author: Nils Törnblom
License-File: LICENSE
License-File: NOTICE
Requires-Python: >=3.10
Requires-Dist: databricks-sdk>=0.20.0
Requires-Dist: pandas>=2.2.3
Requires-Dist: pyarrow>=19.0.1
Requires-Dist: pydantic-settings>=2.7.0
Requires-Dist: pydantic>=2.10.4
Requires-Dist: tqdm>=4.67.1
Requires-Dist: typing-extensions==4.12.2
Provides-Extra: dev
Requires-Dist: hatch>=1.10.0; extra == 'dev'
Requires-Dist: hatchling>=1.27.0; extra == 'dev'
Requires-Dist: mypy>=1.14.1; extra == 'dev'
Requires-Dist: pandas-stubs>=2.2.3.241126; extra == 'dev'
Requires-Dist: pip-licenses>=5.0.0; extra == 'dev'
Requires-Dist: pip>=24.3.1; extra == 'dev'
Requires-Dist: pre-commit>=4.0.1; extra == 'dev'
Requires-Dist: pyright>=1.1.391; extra == 'dev'
Requires-Dist: pyspark>=3.5.0; extra == 'dev'
Requires-Dist: pytest>=8.3.4; extra == 'dev'
Requires-Dist: twine>=5.1.1; extra == 'dev'
Requires-Dist: types-tqdm>=4.67.0.20241221; extra == 'dev'
